dynamotable/__init__.py
dynamotable/analysis.py
dynamotable/constants.py
dynamotable/convention.py
dynamotable/dynamotable.py
dynamotable/io.py
dynamotable/table_map.py
dynamotable/utils.py
dynamotable/version.py
dynamotable-0.2.4.dist-info/LICENSE.txt
dynamotable-0.2.4.dist-info/METADATA
dynamotable-0.2.4.dist-info/WHEEL
dynamotable-0.2.4.dist-info/top_level.txt
dynamotable-0.2.4.dist-info/RECORD
